jupyterlab_cell_autorun_kernel_restart/__init__.py
jupyterlab_cell_autorun_kernel_restart/_version.py
jupyterlab_cell_autorun_kernel_restart/labextension/build_log.json
jupyterlab_cell_autorun_kernel_restart/labextension/package.json
jupyterlab_cell_autorun_kernel_restart/labextension/static/lib_index_js.86f293045c9999a7.js
jupyterlab_cell_autorun_kernel_restart/labextension/static/lib_index_js.86f293045c9999a7.js.map
jupyterlab_cell_autorun_kernel_restart/labextension/static/lib_index_js.ba33bed5778d2f64.js
jupyterlab_cell_autorun_kernel_restart/labextension/static/lib_index_js.ba33bed5778d2f64.js.map
jupyterlab_cell_autorun_kernel_restart/labextension/static/lib_index_js.c5c9b3311d0e2b17.js
jupyterlab_cell_autorun_kernel_restart/labextension/static/lib_index_js.c5c9b3311d0e2b17.js.map
jupyterlab_cell_autorun_kernel_restart/labextension/static/lib_index_js.e717c98a5e199aa8.js
jupyterlab_cell_autorun_kernel_restart/labextension/static/lib_index_js.e717c98a5e199aa8.js.map
jupyterlab_cell_autorun_kernel_restart/labextension/static/remoteEntry.06c58e83ef34876c.js.map
jupyterlab_cell_autorun_kernel_restart/labextension/static/remoteEntry.35731f3ecae9240b.js.map
jupyterlab_cell_autorun_kernel_restart/labextension/static/remoteEntry.436809916a6f4d85.js.map
jupyterlab_cell_autorun_kernel_restart/labextension/static/remoteEntry.6f172b79b726760c.js.map
jupyterlab_cell_autorun_kernel_restart/labextension/static/remoteEntry.84de152d1e8df44f.js.map
jupyterlab_cell_autorun_kernel_restart/labextension/static/remoteEntry.a5c18adf573a1343.js.map
jupyterlab_cell_autorun_kernel_restart/labextension/static/remoteEntry.f6797a32c6276678.js
jupyterlab_cell_autorun_kernel_restart/labextension/static/remoteEntry.f6797a32c6276678.js.map
jupyterlab_cell_autorun_kernel_restart/labextension/static/style.js
jupyterlab_cell_autorun_kernel_restart/labextension/static/style_index_js.754a798f8e34c25a.js
jupyterlab_cell_autorun_kernel_restart-0.5.0.dist-info/LICENSE
jupyterlab_cell_autorun_kernel_restart-0.5.0.dist-info/METADATA
jupyterlab_cell_autorun_kernel_restart-0.5.0.dist-info/WHEEL
jupyterlab_cell_autorun_kernel_restart-0.5.0.dist-info/top_level.txt
jupyterlab_cell_autorun_kernel_restart-0.5.0.dist-info/RECORD
