Metadata-Version: 2.1
Name: jupyterlab_cell_autorun_kernel_restart
Version: 0.5.0
Summary: Define a set of cells as initialization code cells for the kernel. Different scenes may be defined and selected for kernel initialization.
Home-page: https://github.com/schmidi314/jupyterlab_cell_autorun_kernel_restart
Author: Manuel Schmidt
Author-email: Manuel.J.Schmidt@t-online.de
License: BSD-3-Clause
Keywords: Jupyter,JupyterLab,JupyterLab3
Platform: Linux
Platform: Mac OS X
Platform: Windows
Classifier: License :: OSI Approved :: BSD License
Classifier: Programming Language :: Python
Classifier: Programming Language :: Python :: 3
Classifier: Programming Language :: Python :: 3.6
Classifier: Programming Language :: Python :: 3.7
Classifier: Programming Language :: Python :: 3.8
Classifier: Programming Language :: Python :: 3.9
Classifier: Framework :: Jupyter
Classifier: Framework :: Jupyter :: JupyterLab
Classifier: Framework :: Jupyter :: JupyterLab :: 3
Classifier: Framework :: Jupyter :: JupyterLab :: Extensions
Classifier: Framework :: Jupyter :: JupyterLab :: Extensions :: Prebuilt
Requires-Python: >=3.6
License-File: LICENSE
